{
  "name": "grill",
  "plural": "grills",
  "base": "PersistedModel",
  "idInjection": true,
  "options": {
    "validateUpsert": true
  },
  "properties": {
    "id": {
      "type": "number",
      "required": true
    },
    "name": {
      "type": "string",
      "required": true,
      "default": "Grill"
    },
    "description": {
      "type": "string",
      "required": false
    },
    "grilltype": {
      "type": "string",
      "required": true
    },
    "position": {
      "type": "geopoint",
      "required": true
    },
    "verfuegbar": {
      "type": "boolean",
      "default": true
    }
  },
  "validations": [],
  "relations": {},
  "acls": [],
  "methods": {}
}
